README.rst
setup.py
bizdates/__init__.py
bizdates/bizdates.py
bizdates.egg-info/PKG-INFO
bizdates.egg-info/SOURCES.txt
bizdates.egg-info/dependency_links.txt
bizdates.egg-info/requires.txt
bizdates.egg-info/top_level.txt